kleantext/__init__.py
kleantext/preprocessor.py
kleantext-0.1.4.dist-info/METADATA
kleantext-0.1.4.dist-info/WHEEL
kleantext-0.1.4.dist-info/top_level.txt
kleantext-0.1.4.dist-info/RECORD
