Metadata-Version: 2.2
Name: kleantext
Version: 0.1.4
Summary: A Python module for preprocessing text for NLP tasks
Home-page: https://github.com/karan9970/kleantext
Author: Karan
Author-email: Karansd00@gmail.com
License: MIT
Classifier: Programming Language :: Python :: 3
Classifier: License :: OSI Approved :: MIT License
Classifier: Operating System :: OS Independent
Requires-Python: >=3.7
Requires-Dist: textblob>=0.15.3
Requires-Dist: nltk>=3.7
Dynamic: author
Dynamic: author-email
Dynamic: classifier
Dynamic: description
Dynamic: description-content-type
Dynamic: home-page
Dynamic: license
Dynamic: requires-dist
Dynamic: requires-python
Dynamic: summary
